copyaid/__init__.py
copyaid/__main__.py
copyaid/cli.py
copyaid/core.py
copyaid/diff.py
copyaid/task.py
copyaid/util.py
copyaid/config/copyaid.toml
copyaid/config/heavy.toml
copyaid/config/light.toml
copyaid/config/proofread.toml
copyaid-0.7.1.dist-info/METADATA
copyaid-0.7.1.dist-info/WHEEL
copyaid-0.7.1.dist-info/entry_points.txt
copyaid-0.7.1.dist-info/licenses/LICENSE
copyaid-0.7.1.dist-info/RECORD
