Metadata-Version: 2.1
Name: copyaid
Version: 0.7.1
Summary: Copyedit with OpenAI from a CLI.
Project-URL: Homepage, https://gitlab.com/castedo/copyaid
Author: Castedo Ellerman
License: MIT License
License-File: LICENSE
Classifier: License :: OSI Approved :: MIT License
Classifier: Operating System :: POSIX
Classifier: Programming Language :: Python :: 3
Requires-Python: >=3.9
Requires-Dist: openai>=1
Requires-Dist: tomli
Provides-Extra: all
Requires-Dist: jsoml; extra == 'all'
